{
  "LBN": {
    "country": "Lebanon",
    "firstNames": [
      "Hassan", "Bassel", "Hilal", "Joan", "Rabih", "Nader", "Omar", "Abbas", "Khalil", "Mohammed",
      "Ahmad", "Ali", "Amara", "Bilal", "Fadi", "Hadi", "Hussein", "Karim", "Mahdi", "Mohamad",
      "Nour", "Rami", "Salam", "Walid", "Youssef", "Ziad", "Antoine", "Carmel", "Elie", "Georges",
      "Jean", "Khalil", "Maroun", "Nicolas", "Pierre", "Robert", "Samir", "Tony", "Wadih", "Youssef",
      "Abdel", "Fouad", "Ghassan", "Imad", "Jihad", "Kassem", "Marwan", "Nazih", "Riad", "Tariq",
      "Wael", "Zaki", "Amin", "Charbel", "Elias", "Ibrahim", "Jamil", "Mazen", "Rafik", "Salim"
    ],
    "surnames": [
      "El Dor", "Melki", "Maatouk", "Kdouh", "Antar", "Sabra", "Fajr", "Gharzeddine", "Khalil", "Korjie",
      "Nassar", "Oueiss", "Saad", "Tawil", "Zreik", "Alameddine", "Chahrour", "Darwish", "Haidar", "Itani",
      "Jradi", "Khoury", "Mokdad", "Rashid", "Sleiman", "Wehbe", "Abou Khalil", "Bzeih", "Dagher", "Faour",
      "Harb", "Jaafar", "Kanaan", "Makki", "Noureddine", "Salameh", "Yazbeck", "Atallah", "Chehab", "Eid",
      "Ghanem", "Hijazi", "Jawad", "Karam", "Nehme", "Ramadan", "Skaff", "Zgheib", "Awada", "Dabbagh",
      "Fakhreddine", "Hashem", "Iskandar", "Kallas", "Matar", "Noun", "Rihane", "Taleb", "Zeidan", "Ayoub"
    ]
  },
  "PSE": {
    "country": "Palestine",
    "firstNames": [
      "Mahmoud", "Musab", "Tamer", "Mohammed", "Yaser", "Rami", "Omar", "Khaled", "Ahmad", "Ali",
      "Hassan", "Ibrahim", "Salah", "Nasser", "Walid", "Tariq", "Samir", "Fadi", "Karim", "Hadi",
      "Bilal", "Amjad", "Basel", "Fouad", "Ghassan", "Imad", "Jihad", "Kassem", "Marwan", "Nazih",
      "Riad", "Wael", "Zaki", "Abdel", "Amin", "Charbel", "Elias", "Jamil", "Mazen", "Rafik",
      "Salim", "Antoine", "Carmel", "Elie", "Georges", "Jean", "Maroun", "Nicolas", "Pierre", "Robert",
      "Tony", "Wadih", "Youssef", "Abdallah", "Emad", "Hazem", "Isam", "Majdi", "Nabil", "Salam"
    ],
    "surnames": [
      "Abu Warda", "Saleh", "Kharoub", "Dabbagh", "Zeidan", "Seyam", "Jaber", "Faraj", "Khalil", "Qaneer",
      "Rashid", "Abunada", "Darwish", "Mahagni", "Salahat", "Bahdari", "Conté", "Islame", "Maraaba", "Yousef",
      "Amour", "Bahdari", "Canaan", "Dheeb", "Harb", "Jaber", "Kharoub", "Maraaba", "Qaneer", "Salahat",
      "Zeidan", "Abu Warda", "Dabbagh", "Faraj", "Islame", "Khalil", "Mahagni", "Rashid", "Seyam", "Yousef",
      "Abunada", "Conté", "Darwish", "Saleh", "Amour", "Bahdari", "Dheeb", "Harb", "Jaber", "Kharoub",
      "Maraaba", "Qaneer", "Salahat", "Zeidan", "Abu Warda", "Dabbagh", "Faraj", "Islame", "Khalil", "Mahagni"
    ]
  },
  "YEM": {
    "country": "Yemen",
    "firstNames": [
      "Ahmed", "Ali", "Mohammed", "Saleh", "Omar", "Hassan", "Khalid", "Nasser", "Yasser", "Abdallah",
      "Mahmoud", "Ibrahim", "Walid", "Tariq", "Samir", "Fadi", "Karim", "Hadi", "Bilal", "Amjad",
      "Basel", "Fouad", "Ghassan", "Imad", "Jihad", "Kassem", "Marwan", "Nazih", "Riad", "Wael",
      "Zaki", "Abdel", "Amin", "Elias", "Jamil", "Mazen", "Rafik", "Salim", "Abdulrahman", "Adel",
      "Anwar", "Essam", "Farid", "Hamza", "Ismail", "Jamal", "Khaled", "Medhat", "Noureddine", "Osama",
      "Reda", "Sherif", "Wissam", "Zakaria", "Ashraf", "Emad", "Hany", "Mostafa", "Ramzi", "Samy"
    ],
    "surnames": [
      "Al-Dahi", "Al-Hamdani", "Al-Sanabani", "Al-Yafei", "Ba Wazir", "Hadhrami", "Mokbel", "Nagi", "Rashad", "Saleh",
      "Al-Absi", "Al-Gahwi", "Al-Matari", "Al-Selwi", "Ba Mahdi", "Hawsawi", "Noman", "Qasem", "Saeed", "Talib",
      "Al-Akwa", "Al-Hashdi", "Al-Moayed", "Al-Subaihi", "Ba Nagm", "Jubran", "Obadi", "Radfan", "Shaibi", "Thabet",
      "Al-Ansi", "Al-Iryani", "Al-Najjar", "Al-Wazir", "Ba Rayan", "Kaid", "Othmani", "Rajeh", "Soqatri", "Wahid",
      "Al-Arashi", "Al-Kathiri", "Al-Qadhi", "Ba Abbad", "Ba Saeed", "Mahfoudh", "Radman", "Shamsan", "Yafai", "Zaher",
      "Al-Dhubhani", "Al-Marwani", "Al-Sanhani", "Ba Dhib", "Ba Wazir", "Nagi", "Rashad", "Thabit", "Zaidi", "Zubaidi"
    ]
  },
  "OMN": {
    "country": "Oman",
    "firstNames": [
      "Ahmed", "Ali", "Khalid", "Mohammed", "Omar", "Salim", "Sultan", "Abdullah", "Hassan", "Ibrahim",
      "Nasser", "Rashid", "Saeed", "Tariq", "Waleed", "Yasser", "Abdulaziz", "Fahad", "Hamad", "Majed",
      "Mansour", "Nawaf", "Raed", "Saad", "Talal", "Yazeed", "Adel", "Bandar", "Faisal", "Hatim",
      "Hussain", "Khalil", "Maan", "Muteb", "Osama", "Rayan", "Sami", "Turki", "Yousef", "Ziad",
      "Abdulfattah", "Abdulelah", "Bader", "Fahd", "Ghanem", "Hattan", "Jamal", "Laith", "Mohannad", "Nayef",
      "Othman", "Riyadh", "Saud", "Thamer", "Wael", "Abdulmajeed", "Ahmad", "Feras", "Hamza", "Mishaal"
    ],
    "surnames": [
      "Al-Rushaidi", "Al-Alawi", "Al-Ghassani", "Al-Harthi", "Al-Jabri", "Al-Kindi", "Al-Lawati", "Al-Mahrooqi", "Al-Mandhari", "Al-Muscat",
      "Al-Naziri", "Al-Rahbi", "Al-Rawahi", "Al-Siyabi", "Al-Wahaibi", "Al-Zadjali", "Ambusaidi", "Ba Omar", "Habsi", "Haddabi",
      "Al-Aghbari", "Al-Busaidi", "Al-Farsi", "Al-Hinai", "Al-Kalbani", "Al-Maamari", "Al-Mukhaini", "Al-Nabhani", "Al-Qasmi", "Al-Saadi",
      "Al-Shukaili", "Al-Tamimi", "Al-Yarubi", "Amur", "Fawzi", "Kashem", "Al-Dhuhli", "Al-Habsi", "Al-Kamali", "Al-Musawi",
      "Al-Rashdi", "Al-Salami", "Al-Zakwani", "Amour", "Haitham", "Mubarak", "Al-Fazari", "Al-Hosni", "Al-Khalasi", "Al-Naabi",
      "Al-Riyami", "Al-Shamsi", "Amri", "Bait Said", "Juma", "Said", "Al-Ghafri", "Al-Ismaili", "Al-Kharusi", "Al-Raisi"
    ]
  },
  "UAE": {
    "country": "UAE",
    "firstNames": [
      "Ahmed", "Ali", "Omar", "Mohammed", "Khalid", "Abdullah", "Salem", "Sultan", "Hassan", "Rashid",
      "Hamdan", "Majed", "Saeed", "Nasser", "Waleed", "Tariq", "Yasser", "Abdulaziz", "Fahad", "Hamad",
      "Mansour", "Nawaf", "Raed", "Saad", "Talal", "Yazeed", "Adel", "Bandar", "Faisal", "Hatim",
      "Hussain", "Khalil", "Maan", "Muteb", "Osama", "Rayan", "Sami", "Turki", "Yousef", "Ziad",
      "Abdulfattah", "Abdulelah", "Bader", "Fahd", "Ghanem", "Hattan", "Jamal", "Laith", "Mohannad", "Nayef",
      "Othman", "Riyadh", "Saud", "Thamer", "Wael", "Abdulmajeed", "Ahmad", "Feras", "Hamza", "Mishaal"
    ],
    "surnames": [
      "Al-Ahbabi", "Al-Ameri", "Al-Dhaheri", "Al-Hammadi", "Al-Junaibi", "Al-Kaabi", "Al-Ketbi", "Al-Mansoori", "Al-Mazrouei", "Al-Muhairi",
      "Al-Neyadi", "Al-Qubaisi", "Al-Shamsi", "Al-Suwaidi", "Al-Zaabi", "Abdulrahman", "Jumaa", "Khalil", "Mabkhout", "Rashid",
      "Al-Attas", "Al-Blooshi", "Al-Ghafli", "Al-Hosani", "Al-Khaili", "Al-Marzooqi", "Al-Mehairbi", "Al-Nuaimi", "Al-Rashid", "Al-Shehhi",
      "Al-Tamimi", "Awana", "Khamis", "Majid", "Sebait", "Al-Balooshi", "Al-Dhanhani", "Al-Hashemi", "Al-Kamali", "Al-Matrooshi",
      "Al-Mutawa", "Al-Romaithi", "Al-Shamsi", "Al-Tunaiji", "Darwish", "Mahdi", "Saleh", "Al-Braiki", "Al-Gheilani", "Al-Jenaibi",
      "Al-Maazmi", "Al-Naqbi", "Al-Salmeen", "Al-Tayer", "Al-Yafei", "Juma", "Omar", "Sultan", "Al-Fahim", "Al-Maktoum"
    ]
  },
  "QAT": {
    "country": "Qatar",
    "firstNames": [
      "Hassan", "Akram", "Pedro", "Saad", "Boualem", "Karim", "Abdelkarim", "Almahdi", "Assim", "Khalid",
      "Mohammed", "Meshaal", "Ahmed", "Abdulrahman", "Ismail", "Homam", "Tarek", "Yusuf", "Abdulaziz", "Jassim",
      "Salem", "Abdullah", "Ali", "Omar", "Nasser", "Rashid", "Saeed", "Sultan", "Waleed", "Yasser",
      "Adel", "Bandar", "Faisal", "Hamad", "Majed", "Mansour", "Nawaf", "Raed", "Talal", "Yazeed",
      "Abdulfattah", "Abdulelah", "Bader", "Fahd", "Ghanem", "Hattan", "Hatim", "Hussain", "Jamal", "Khalil",
      "Laith", "Maan", "Mohannad", "Muteb", "Nayef", "Osama", "Othman", "Riyadh", "Sami", "Saud"
    ],
    "surnames": [
      "Al-Sheeb", "Afif", "Correia", "Al-Sheeb", "Khoukhi", "Boudiaf", "Hassan", "Ali", "Madibo", "Haydos",
      "Al-Rawi", "Muntari", "Alaaeldin", "Al-Haidos", "Salman", "Ahmed", "Al-Mahdi", "Abdisalam", "Al-Ahmadi", "Fadlalla",
      "Al-Enezi", "Abdullah", "Al-Yazidi", "Tarek", "Al-Kuwari", "Ro-Ro", "Al-Ganehi", "Mendes", "Al-Moez", "Abdu",
      "Al-Ansari", "Al-Baker", "Al-Duhail", "Al-Gharafa", "Al-Haydos", "Al-Jasmi", "Al-Kuwari", "Al-Mahdi", "Al-Marri", "Al-Moez",
      "Al-Naemi", "Al-Rawi", "Al-Sadd", "Al-Tamimi", "Al-Thani", "Boudiaf", "Hassan", "Khoukhi", "Madibo", "Muntari",
      "Afif", "Correia", "Haydos", "Salman", "Tarek", "Alaaeldin", "Al-Ahmadi", "Al-Enezi", "Fadlalla", "Mendes"
    ]
  },
  "BHR": {
    "country": "Bahrain",
    "firstNames": [
      "Ebrahim", "Sayed", "Ali", "Ahmed", "Mohamed", "Mahdi", "Waleed", "Kamil", "Abdulla", "Jasim",
      "Hasan", "Hussein", "Komail", "Rashed", "Abdulwahab", "Jassim", "Mohammed", "Khalid", "Omar", "Nasser",
      "Rashid", "Saeed", "Sultan", "Abdullah", "Hassan", "Ibrahim", "Salim", "Tariq", "Waleed", "Yasser",
      "Adel", "Bandar", "Faisal", "Hamad", "Majed", "Mansour", "Nawaf", "Raed", "Saad", "Talal",
      "Yazeed", "Abdulaziz", "Fahad", "Ghanem", "Hattan", "Hatim", "Hussain", "Jamal", "Khalil", "Laith",
      "Maan", "Mohannad", "Muteb", "Nayef", "Osama", "Othman", "Riyadh", "Sami", "Saud", "Thamer"
    ],
    "surnames": [
      "Rashid", "Al-Romaihi", "Hubail", "Al-Khalas", "Al-Dakhil", "Madan", "Al-Hayam", "Al-Aswad", "Duaij", "Abbas",
      "Sherida", "Juma", "Al-Hardan", "Marhoon", "Al-Mukharraq", "Al-Doseri", "Al-Shamsan", "Al-Mannai", "Bughammar", "Al-Fadhel",
      "Al-Khalifa", "Al-Zayed", "Abdullatif", "Al-Noaimi", "Rabia", "Adel", "Baba", "Faraj", "Ghazal", "Isa",
      "Khalil", "Mirza", "Qambar", "Saeed", "Yusuf", "Al-Ansari", "Al-Buainain", "Al-Mannai", "Al-Thawadi", "Bakhit",
      "Darwish", "Fakhro", "Haji", "Kanoo", "Matrook", "Salman", "Yateem", "Al-Arrayed", "Al-Dosari", "Al-Mutawa",
      "Bahzad", "Dashti", "Hasan", "Janahi", "Murad", "Shehab", "Zubari", "Al-Binali", "Al-Ghanim", "Al-Sulaiti"
    ]
  },
  "KUW": {
    "country": "Kuwait",
    "firstNames": [
      "Sulaiman", "Fahad", "Meshari", "Badr", "Yousef", "Khaled", "Abdullah", "Faisal", "Ahmad", "Bader",
      "Hamad", "Mohammed", "Nasser", "Rashid", "Saeed", "Sultan", "Ali", "Omar", "Hassan", "Ibrahim",
      "Salim", "Tariq", "Waleed", "Yasser", "Adel", "Bandar", "Majed", "Mansour", "Nawaf", "Raed",
      "Saad", "Talal", "Yazeed", "Abdulaziz", "Ghanem", "Hattan", "Hatim", "Hussain", "Jamal", "Khalil",
      "Laith", "Maan", "Mohannad", "Muteb", "Nayef", "Osama", "Othman", "Riyadh", "Sami", "Saud",
      "Thamer", "Wael", "Abdulfattah", "Abdulelah", "Fahd", "Mishaal", "Turki", "Ziad", "Rayan", "Abdulmajeed"
    ],
    "surnames": [
      "Al-Rashidi", "Al-Mutairi", "Al-Harbi", "Al-Otaibi", "Al-Dosari", "Al-Qahtani", "Al-Shammari", "Al-Enezi", "Al-Ajmi", "Al-Fadhli",
      "Al-Kandari", "Al-Azmi", "Al-Shamali", "Al-Sabah", "Al-Awadi", "Al-Duaij", "Al-Fulaij", "Al-Ghanem", "Al-Hajeri", "Al-Kharafi",
      "Al-Mulla", "Al-Nafisi", "Al-Qabandi", "Al-Roumi", "Al-Sabeeh", "Al-Tarkait", "Al-Wazzan", "Behbehani", "Dashti", "Hayat",
      "Marafi", "Shehab", "Al-Bahar", "Al-Essa", "Al-Khalid", "Al-Marzouq", "Al-Rashid", "Al-Saleh", "Al-Sane", "Al-Youha",
      "Boushehri", "Ghloum", "Kuna", "Rashed", "Tabtabaei", "Al-Bader", "Al-Jassim", "Al-Khalifa", "Al-Musallam", "Al-Saad",
      "Al-Salem", "Al-Waqayan", "Dashti", "Issa", "Nasser", "Sultan", "Al-Ahmad", "Al-Jassar", "Al-Maraj", "Al-Sabah"
    ]
  }
}